xtracer/__init__.py
xtracer/__main__.py
xtracer-0.6.dist-info/LICENSE
xtracer-0.6.dist-info/METADATA
xtracer-0.6.dist-info/WHEEL
xtracer-0.6.dist-info/top_level.txt
xtracer-0.6.dist-info/RECORD
