Metadata-Version: 2.1
Name: xtracer
Version: 0.6
Summary: Python Multi Tracer Tool
Home-page: https://github.com/ph-fox/xtracer
Author: Anikin Luke Abales
Author-email: abalesluke@gmail.com
Project-URL: Homepage, https://anikinlukeabales.ninja/projects/xtracer
Project-URL: Source, https://github.com/ph-fox/xtracer
Project-URL: Bug Tracker, https://github.com/ph-fox/xtracer/issues
Classifier: Programming Language :: Python :: 3
Classifier: License :: OSI Approved :: MIT License
Classifier: Operating System :: OS Independent
Requires-Python: >=3.6
License-File: LICENSE
